pyrms/__init__.py
pyrms/rms.py
pyrms/rmsTest.py
pyrms-1.0.1.dist-info/LICENSE
pyrms-1.0.1.dist-info/METADATA
pyrms-1.0.1.dist-info/WHEEL
pyrms-1.0.1.dist-info/top_level.txt
pyrms-1.0.1.dist-info/RECORD
