Metadata-Version: 2.1
Name: pyrms
Version: 1.0.1
Home-page: https://github.com/ReactionMechanismGenerator/pyrms
Author: mjohnson541
Author-email: mjohnson541@gmail.com
Classifier: Programming Language :: Python :: 3
Classifier: License :: OSI Approved :: MIT License
Requires-Python: >=3.7
License-File: LICENSE
